{"code":200,"last_update":1490661420,"data":[{"from":{"id":832,"name":"\u041c\u043e\u0441\u043a\u0432\u0430"},"to":{"id":41,"name":"\u0410\u043b\u043c\u0430\u0442\u044b"},"hotels":[{"stars":3,"curency":"RUB","price":41295.5},{"stars":4,"curency":"RUB","price":46771},{"stars":5,"curency":"RUB","price":77545.5}]},{"from":{"id":832,"name":"\u041c\u043e\u0441\u043a\u0432\u0430"},"to":{"id":2990,"name":"\u0411\u043e\u0440\u043e\u0432\u043e\u0435"},"hotels":[{"stars":1,"curency":"RUB","price":17500},{"stars":3,"curency":"RUB","price":21525}]}]}